stepit/__init__.py
stepit/stepit.py
stepit-0.5.4.dist-info/LICENSE
stepit-0.5.4.dist-info/METADATA
stepit-0.5.4.dist-info/WHEEL
stepit-0.5.4.dist-info/top_level.txt
stepit-0.5.4.dist-info/RECORD
