Metadata-Version: 2.2
Name: stepit
Version: 0.5.4
Summary: Add your description here
Author-email: Eduardo Alfonso-Sierra <edalfon@gmail.com>
Requires-Python: >=3.9
License-File: LICENSE
